head_hunter_job_bot_auth_tool/__init__.py
head_hunter_job_bot_auth_tool/cli.py
head_hunter_job_bot_auth_tool/main.py
head_hunter_job_bot_auth_tool-1.0.3.dist-info/licenses/LICENSE
head_hunter_job_bot_auth_tool-1.0.3.dist-info/METADATA
head_hunter_job_bot_auth_tool-1.0.3.dist-info/WHEEL
head_hunter_job_bot_auth_tool-1.0.3.dist-info/entry_points.txt
head_hunter_job_bot_auth_tool-1.0.3.dist-info/top_level.txt
head_hunter_job_bot_auth_tool-1.0.3.dist-info/RECORD
