Metadata-Version: 2.4
Name: head-hunter-job-bot-auth-tool
Version: 1.0.3
Summary: GUI инструмент для авторизации в HeadHunter API через OAuth
Author-email: HeadHunter Job Bot <noreply@example.com>
Maintainer-email: HeadHunter Job Bot <noreply@example.com>
License: MIT License
Project-URL: Homepage, https://github.com/your-username/head-hunter-job-bot-auth-tool
Project-URL: Repository, https://github.com/your-username/head-hunter-job-bot-auth-tool
Project-URL: Documentation, https://github.com/your-username/head-hunter-job-bot-auth-tool#readme
Project-URL: Bug Tracker, https://github.com/your-username/head-hunter-job-bot-auth-tool/issues
Keywords: headhunter,hh,api,oauth,authorization,gui,job,bot
Classifier: Development Status :: 5 - Production/Stable
Classifier: Intended Audience :: Developers
Classifier: License :: OSI Approved :: MIT License
Classifier: Operating System :: OS Independent
Classifier: Programming Language :: Python :: 3
Classifier: Programming Language :: Python :: 3.9
Classifier: Programming Language :: Python :: 3.10
Classifier: Programming Language :: Python :: 3.11
Classifier: Programming Language :: Python :: 3.12
Classifier: Topic :: Software Development :: Libraries :: Python Modules
Classifier: Topic :: Internet :: WWW/HTTP :: Dynamic Content
Classifier: Topic :: Office/Business
Requires-Python: >=3.9
License-File: LICENSE
Requires-Dist: requests>=2.28.0
Requires-Dist: PyQt6>=6.4.0
Requires-Dist: PyQt6-WebEngine>=6.4.0
Provides-Extra: dev
Requires-Dist: build>=0.10.0; extra == "dev"
Requires-Dist: twine>=4.0.0; extra == "dev"
Dynamic: license-file
